vtda/__init__.py
vtda/requirements.txt
vtda/__pycache__/__init__.cpython-39.pyc
vtda/aum/__init__.py
vtda/aum/aum.py
vtda/aum/__pycache__/__init__.cpython-39.pyc
vtda/aum/__pycache__/aum.cpython-39.pyc
vtda/data_maps/__init__.py
vtda/data_maps/calculators.py
vtda/data_maps/map.py
vtda/data_maps/__pycache__/__init__.cpython-39.pyc
vtda/data_maps/__pycache__/calculators.cpython-39.pyc
vtda/data_maps/__pycache__/map.cpython-39.pyc
vtda/influence_function/__init__.py
vtda/influence_function/calc_influence_function.py
vtda/influence_function/influence_function.py
vtda/influence_function/show_image.py
vtda/influence_function/utils.py
vtda/influence_function/__pycache__/__init__.cpython-39.pyc
vtda/influence_function/__pycache__/calc_influence_function.cpython-39.pyc
vtda/influence_function/__pycache__/influence_function.cpython-39.pyc
vtda/influence_function/__pycache__/show_image.cpython-39.pyc
vtda/influence_function/__pycache__/utils.cpython-39.pyc
vtda/repair/__init__.py
vtda/repair/datasets.py
vtda/repair/measure.py
vtda/repair/models.py
vtda/repair/repair.py
vtda/training_dynamics/AreaUnderTheMarginRanking.py
vtda/training_dynamics/TrainingDynamics.py
vtda/training_dynamics/__init__.py
vtda/training_dynamics/__pycache__/AreaUnderTheMarginRanking.cpython-39.pyc
vtda/training_dynamics/__pycache__/TrainingDynamics.cpython-39.pyc
vtda/training_dynamics/__pycache__/__init__.cpython-39.pyc
su_vtda-0.2.0.dist-info/METADATA
su_vtda-0.2.0.dist-info/WHEEL
su_vtda-0.2.0.dist-info/top_level.txt
su_vtda-0.2.0.dist-info/RECORD
