Metadata-Version: 2.1
Name: su-vtda
Version: 0.2.0
Summary: Visual Training Dynamics Analysis Library
Home-page: https://github.com/ekcmert/VTDA
Author: Mert Ekici
Author-email: ekicimert@sabancinuiv.edu
License: Sabanci University
Platform: UNKNOWN
Classifier: Intended Audience :: Developers
Classifier: License :: Free For Educational Use
Classifier: Programming Language :: Python
Classifier: Programming Language :: Python :: 3
Classifier: Programming Language :: Python :: 3.6
Classifier: Programming Language :: Python :: 3.7
Classifier: Programming Language :: Python :: 3.8
Classifier: Programming Language :: Python :: 3.9
Classifier: Operating System :: OS Independent
Requires-Dist: numpy
Requires-Dist: matplotlib
Requires-Dist: torch
Requires-Dist: pandas
Requires-Dist: seaborn
Requires-Dist: scipy
